bomberman/__init__.py
bomberman/client.py
bomberman/communications.py
bomberman/editor.py
bomberman/game.py
bomberman/server.py
bomberman/sprites.py
bbomberman-0.0.1.dist-info/LICENSE
bbomberman-0.0.1.dist-info/METADATA
bbomberman-0.0.1.dist-info/WHEEL
bbomberman-0.0.1.dist-info/top_level.txt
bbomberman-0.0.1.dist-info/RECORD
