Metadata-Version: 2.1
Name: bbomberman
Version: 0.0.1
Summary: Bomberman the game
Home-page: UNKNOWN
Author: Hyperbodya
Author-email: smartcookier@gmail.com
License: UNKNOWN
Platform: UNKNOWN
Classifier: Programming Language :: Python :: 3
Classifier: License :: OSI Approved :: MIT License
Classifier: Operating System :: OS Independent
